[1,["6f3eg8ZkxGsKtS9SayOXWa","157a51c2a"],["spriteFrame","_textureSetter"],["cc.SpriteFrame",["cc.BitmapFont",["_name","fontSize","_fntConfig"],0]],[[1,0,1,2,4]],[[[[0,"zy_yxz_T-export2x",32,{"commonHeight":60,"fontSize":32,"atlasName":"G:\\apk消星星\\文字\\zy_yxz_T-export2x.png","fontDefDictionary":{"9":{"xOffset":0,"yOffset":0,"xAdvance":216,"rect":{"x":0,"y":0,"width":0,"height":0}},"32":{"xOffset":0,"yOffset":0,"xAdvance":27,"rect":{"x":0,"y":0,"width":0,"height":0}},"48":{"xOffset":0,"yOffset":8,"xAdvance":35,"rect":{"x":39,"y":0,"width":34,"height":52}},"49":{"xOffset":0,"yOffset":8,"xAdvance":22,"rect":{"x":110,"y":0,"width":21,"height":52}},"50":{"xOffset":0,"yOffset":8,"xAdvance":36,"rect":{"x":0,"y":108,"width":35,"height":51}},"51":{"xOffset":0,"yOffset":8,"xAdvance":36,"rect":{"x":0,"y":54,"width":35,"height":52}},"52":{"xOffset":0,"yOffset":8,"xAdvance":38,"rect":{"x":0,"y":0,"width":37,"height":52}},"53":{"xOffset":0,"yOffset":9,"xAdvance":34,"rect":{"x":74,"y":108,"width":33,"height":51}},"54":{"xOffset":0,"yOffset":8,"xAdvance":35,"rect":{"x":74,"y":54,"width":34,"height":52}},"55":{"xOffset":0,"yOffset":9,"xAdvance":36,"rect":{"x":37,"y":108,"width":35,"height":51}},"56":{"xOffset":0,"yOffset":8,"xAdvance":36,"rect":{"x":37,"y":54,"width":35,"height":52}},"57":{"xOffset":0,"yOffset":8,"xAdvance":34,"rect":{"x":75,"y":0,"width":33,"height":52}}},"kerningDict":{}}]],0,0,[0],[0],[0]],[[{"name":"zy_yxz_T-export2x","rect":[798,937,131,159],"offset":[-1,1],"originalSize":[133,161],"capInsets":[0,0,0,0]}],[0],0,[0],[1],[1]]]]