[1,["11f680510@6c48a"],["_textureSource"],["cc.SpriteFrame"],0,[[[{"name":"sp_play","rect":{"x":3,"y":3,"width":400,"height":140},"offset":{"x":0,"y":0},"originalSize":{"width":400,"height":140},"rotated":false,"capInsets":[0,0,0,0],"packable":true,"pixelsToUnit":100,"pivot":{"x":0.5,"y":0.5},"meshType":0}],[0],0,[0],[0],[0]],[[{"name":"sp_music_close","rect":{"x":373,"y":455,"width":78,"height":83},"offset":{"x":0,"y":0},"originalSize":{"width":78,"height":83},"rotated":true,"capInsets":[0,0,0,0],"packable":true,"pixelsToUnit":100,"pivot":{"x":0.5,"y":0.5},"meshType":0}],[0],0,[0],[0],[0]],[[{"name":"sp_music_open","rect":{"x":373,"y":539,"width":78,"height":83},"offset":{"x":0,"y":0},"originalSize":{"width":78,"height":83},"rotated":true,"capInsets":[0,0,0,0],"packable":true,"pixelsToUnit":100,"pivot":{"x":0.5,"y":0.5},"meshType":0}],[0],0,[0],[0],[0]],[[{"name":"sp_btn_cangku","rect":{"x":409,"y":3,"width":220,"height":100},"offset":{"x":0,"y":0},"originalSize":{"width":220,"height":100},"rotated":true,"capInsets":[0,0,0,0],"packable":true,"pixelsToUnit":100,"pivot":{"x":0.5,"y":0.5},"meshType":0}],[0],0,[0],[0],[0]],[[{"name":"sp_sp","rect":{"x":462,"y":536,"width":23,"height":16},"offset":{"x":0,"y":0},"originalSize":{"width":23,"height":16},"rotated":false,"capInsets":[0,0,0,0],"packable":true,"pixelsToUnit":100,"pivot":{"x":0.5,"y":0.5},"meshType":0}],[0],0,[0],[0],[0]],[[{"name":"sp_go_back","rect":{"x":373,"y":623,"width":69,"height":72},"offset":{"x":0,"y":0},"originalSize":{"width":69,"height":72},"rotated":false,"capInsets":[0,0,0,0],"packable":true,"pixelsToUnit":100,"pivot":{"x":0.5,"y":0.5},"meshType":0}],[0],0,[0],[0],[0]],[[{"name":"sp_putongmo","rect":{"x":3,"y":455,"width":364,"height":287},"offset":{"x":0,"y":0},"originalSize":{"width":364,"height":287},"rotated":false,"capInsets":[0,0,0,0],"packable":true,"pixelsToUnit":100,"pivot":{"x":0.5,"y":0.5},"meshType":0}],[0],0,[0],[0],[0]],[[{"name":"sp_putongmo2","rect":{"x":3,"y":149,"width":384,"height":287},"offset":{"x":0,"y":0},"originalSize":{"width":384,"height":287},"rotated":false,"capInsets":[0,0,0,0],"packable":true,"pixelsToUnit":100,"pivot":{"x":0.5,"y":0.5},"meshType":0}],[0],0,[0],[0],[0]],[[{"name":"sp_tili","rect":{"x":462,"y":455,"width":29,"height":45},"offset":{"x":0,"y":0},"originalSize":{"width":29,"height":45},"rotated":true,"capInsets":[0,0,0,0],"packable":true,"pixelsToUnit":100,"pivot":{"x":0.5,"y":0.5},"meshType":0}],[0],0,[0],[0],[0]],[[{"name":"sp_goid","rect":{"x":462,"y":490,"width":40,"height":40},"offset":{"x":0,"y":0},"originalSize":{"width":40,"height":40},"rotated":false,"capInsets":[0,0,0,0],"packable":true,"pixelsToUnit":100,"pivot":{"x":0.5,"y":0.5},"meshType":0}],[0],0,[0],[0],[0]],[[{"name":"sp_xuanzejiantou","rect":{"x":448,"y":623,"width":53,"height":61},"offset":{"x":0,"y":0},"originalSize":{"width":53,"height":61},"rotated":true,"capInsets":[0,0,0,0],"packable":true,"pixelsToUnit":100,"pivot":{"x":0.5,"y":0.5},"meshType":0}],[0],0,[0],[0],[0]],[[{"name":"sp_btn_juese","rect":{"x":393,"y":229,"width":220,"height":100},"offset":{"x":0,"y":0},"originalSize":{"width":220,"height":100},"rotated":true,"capInsets":[0,0,0,0],"packable":true,"pixelsToUnit":100,"pivot":{"x":0.5,"y":0.5},"meshType":0}],[0],0,[0],[0],[0]]]]
