[1,["1cc9aa8f5"],["_textureSetter"],["cc.SpriteFrame"],0,[[[{"name":"suibaoshi_blue04","rect":[56,929,17,18],"offset":[0,0],"originalSize":[17,18],"rotated":1,"capInsets":[0,0,0,0]}],[0],0,[0],[0],[0]],[[{"name":"suibaoshi_blue02","rect":[36,777,21,23],"offset":[0,0],"originalSize":[21,23],"rotated":1,"capInsets":[0,0,0,0]}],[0],0,[0],[0],[0]],[[{"name":"suibaoshi_blue03","rect":[3,859,19,23],"offset":[0,0],"originalSize":[19,23],"rotated":1,"capInsets":[0,0,0,0]}],[0],0,[0],[0],[0]],[[{"name":"suibaoshi_blue01","rect":[3,777,27,22],"offset":[0,0],"originalSize":[27,22],"capInsets":[0,0,0,0]}],[0],0,[0],[0],[0]]]]